nesp_lib/__init__.py
nesp_lib/alarm_status.py
nesp_lib/exceptions.py
nesp_lib/port.py
nesp_lib/pump.py
nesp_lib/pumping_direction.py
nesp_lib/status.py
NESP_Lib-1.0.3.dist-info/LICENSE.txt
NESP_Lib-1.0.3.dist-info/METADATA
NESP_Lib-1.0.3.dist-info/WHEEL
NESP_Lib-1.0.3.dist-info/top_level.txt
NESP_Lib-1.0.3.dist-info/RECORD
