Metadata-Version: 2.1
Name: NESP-Lib
Version: 1.0.3
Summary: New Era Syringe Pump Library for Python
Home-page: https://github.com/florian-lapp/nesp-lib-py
Author: Florian Lapp
Author-email: e5abed0c@gmail.com
License: MIT
Keywords: New-Era-Pump-Systems,Syringe-Pump
Classifier: Development Status :: 5 - Production/Stable
Classifier: Intended Audience :: Developers
Classifier: Intended Audience :: Science/Research
Classifier: License :: OSI Approved :: MIT License
Classifier: Operating System :: OS Independent
Classifier: Typing :: Typed
License-File: LICENSE.txt
Requires-Dist: pyserial
